cmapps/__init__.py
cmapps/neon/__init__.py
cmapps/neon/neon.py
cmapps/neon/core/__init__.py
cmapps/neon/core/definitions.py
cmapps/neon/core/mainapplication.py
cmapps/neon/core/preferences.py
cmapps/neon/core/misc/__init__.py
cmapps/neon/core/misc/neonerror.py
cmapps/neon/core/serializers/__init__.py
cmapps/neon/core/serializers/base.py
cmapps/neon/core/serializers/identifiervalue.py
cmapps/neon/core/serializers/json.py
cmapps/neon/settings/__init__.py
cmapps/neon/settings/mainsettings.py
cmapps/neon/undoredo/__init__.py
cmapps/neon/undoredo/commands.py
cmapps/neon/view/__init__.py
cmapps/neon/view/icons_rc.py
cmapps/neon/view/mainwindow.py
cmapps/neon/view/ui_mainwindow.py
cmapps/neon/view/dialogs/__init__.py
cmapps/neon/view/dialogs/aboutdialog.py
cmapps/neon/view/dialogs/ui_aboutdialog.py
cmapps/neon/view/misc/__init__.py
cmapps/neon/view/misc/scientificdoublespinbox.py
cmapps_neon-4.0.0b5.dist-info/LICENSE
cmapps_neon-4.0.0b5.dist-info/METADATA
cmapps_neon-4.0.0b5.dist-info/WHEEL
cmapps_neon-4.0.0b5.dist-info/entry_points.txt
cmapps_neon-4.0.0b5.dist-info/top_level.txt
cmapps_neon-4.0.0b5.dist-info/RECORD
