Metadata-Version: 2.2
Name: cmapps.neon
Version: 4.0.0b5
Summary: A visualisation application for finite element models described with (nominally) cubic-Hermite elements.
Author-email: Hugh Sorby <h.sorby@auckland.ac.nz>
License: 
Project-URL: Homepage, https://cmlibs.org
Project-URL: Repository, https://github.com/CMLibs/cmapps.neon
Keywords: CMLibs,Zinc,Visualisation,Finite Element
Classifier: Programming Language :: Python :: 3
Classifier: License :: OSI Approved :: Apache Software License
Classifier: Operating System :: OS Independent
Classifier: Topic :: Scientific/Engineering :: Medical Science Apps.
Classifier: Topic :: Scientific/Engineering :: Visualization
Requires-Python: >=3.8
License-File: LICENSE
Requires-Dist: cmlibs.utils
Requires-Dist: PySide6
Requires-Dist: cmlibs.zinc
Requires-Dist: cmlibs.widgets
Requires-Dist: cmlibs.argon
